tpfi/__init__.py
tpfi/tpfi.py
tpfi/utils.py
tpfi/version.py
tpfi-1.2.5.dist-info/LICENSE
tpfi-1.2.5.dist-info/METADATA
tpfi-1.2.5.dist-info/WHEEL
tpfi-1.2.5.dist-info/RECORD
