Metadata-Version: 2.3
Name: tpfi
Version: 1.2.5
Summary: Plot identification charts for Kepler, K2 and TESS.
License: MIT
Author: Keyu Xing
Author-email: kyxing@mail.bnu.edu.cn
Requires-Python: >=3.9
Classifier: License :: OSI Approved :: MIT License
Classifier: Programming Language :: Python :: 3
Classifier: Programming Language :: Python :: 3.9
Classifier: Programming Language :: Python :: 3.10
Classifier: Programming Language :: Python :: 3.11
Classifier: Programming Language :: Python :: 3.12
Classifier: Programming Language :: Python :: 3.13
Requires-Dist: lightkurve (>=2.4.2)
Project-URL: Homepage, https://github.com/keyuxing/tpfi
Project-URL: Repository, https://github.com/keyuxing/tpfi
